[
    {
        "id": 4,
        "title": "Link-Up!", 
        "gitHub": "https://github.com/MattMurn/Link-Up",
        "description": "",
        "deployment": "https://linkupapp.herokuapp.com/",
        "src": "./assets/img/LinkUp.jpg"
    },
    {
        "id": 1,
        "title": "Mentorize", 
        "gitHub": "https://github.com/elliechen321/Mentor_Matching_App/tree/developer",
        "description": "",
        "deployment": "https://github.com/elliechen321/Mentor_Matching_App/tree/developer",
        "src": "./assets/img/mentor.png"
    },
    {
        "id": 2, 
        "title": "MongoFullstack App", 
        "gitHub": "https://github.com/MattMurn/mongoNews",
        "description": "",
        "deployment": "https://mongonewsapp.herokuapp.com/",
        "src": "./assets/img/mongonews.png"
    },
    {
        "id": 3,
        "title": " Node | Sql App", 
        "gitHub": "https://github.com/MattMurn/BamazonNodeApp",
        "description": "",
        "deployment": "https://www.youtube.com/watch?v=Y4r7S2tTYd0&feature=youtu.be",
        "src": "./assets/img/nodeapp.gif"
    }
    
]